pywwt/__init__.py
pywwt/_version.py
pywwt/annotation.py
pywwt/app.py
pywwt/conftest.py
pywwt/core.py
pywwt/data_server.py
pywwt/imagery.py
pywwt/instruments.py
pywwt/jupyter.py
pywwt/jupyter_server.py
pywwt/layers.py
pywwt/logger.py
pywwt/qt.py
pywwt/solar_system.py
pywwt/traits.py
pywwt/utils.py
pywwt/labextension/pywwt-0.9.0.tgz
pywwt/nbextension/__init__.py
pywwt/nbextension/static/extension.js
pywwt/nbextension/static/index.js
pywwt/nbextension/static/index.js.map
pywwt/nbextension/static/wwt.html
pywwt/nbextension/static/wwt_json_api.js
pywwt/nbextension/static/interactive_figure/index.html
pywwt/nbextension/static/interactive_figure/interactive_figure.js
pywwt/tests/__init__.py
pywwt/tests/test_core.py
pywwt/tests/test_layers.py
pywwt/tests/test_qt_widget.py
pywwt/tests/test_serialization.py
pywwt/tests/data/webengine/image_layer_equ.png
pywwt/tests/data/webengine/image_layer_gal.png
pywwt/tests/data/webengine/sky_layers.png
pywwt/tests/data/webengine/sky_layers_cartesian.png
pywwt/tests/data/webengine/test_full_step0.png
pywwt/tests/data/webengine/test_full_step1.png
pywwt/tests/data/webengine/test_full_step2.png
pywwt/tests/data/webengine/test_full_step3.png
pywwt/tests/data/webengine/test_full_step4.png
pywwt/tests/data/webengine/test_full_step5.png
pywwt/tests/data/webengine_mesa/test_full_step2.png
pywwt/tests/data/webengine_mesa/test_full_step3.png
pywwt/tests/data/webengine_mesa/test_full_step4.png
pywwt/tests/data/webengine_mesa/test_full_step5.png
pywwt/tests/data/webengine_osx/image_layer_equ.png
pywwt/tests/data/webengine_osx/image_layer_gal.png
pywwt/tests/data/webengine_osx/sky_layers.png
pywwt/tests/data/webengine_osx/sky_layers_cartesian.png
pywwt/tests/data/webengine_osx/test_full_step0.png
pywwt/tests/data/webengine_osx/test_full_step1.png
pywwt/tests/data/webengine_osx/test_full_step2.png
pywwt/tests/data/webengine_osx/test_full_step3.png
pywwt/tests/data/webengine_osx/test_full_step4.png
pywwt/tests/data/webengine_osx/test_full_step5.png
pywwt-0.9.0.dist-info/LICENSE.rst
pywwt-0.9.0.dist-info/METADATA
pywwt-0.9.0.dist-info/WHEEL
pywwt-0.9.0.dist-info/top_level.txt
pywwt-0.9.0.dist-info/RECORD
