Metadata-Version: 2.1
Name: pywwt
Version: 0.9.0
Summary: The AAS WorldWide Telescope from Python
Home-page: https://github.com/WorldWideTelescope/pywwt
Author: Thomas P. Robitaille, O. Justin Otor, and John ZuHone
Author-email: thomas.robitaille@gmail.com
License: BSD
Keywords: Jupyter,Widgets,IPython
Platform: Linux
Platform: Mac OS X
Platform: Windows
Classifier: Intended Audience :: Developers
Classifier: Intended Audience :: Science/Research
Classifier: License :: OSI Approved :: BSD License
Classifier: Topic :: Multimedia :: Graphics
Classifier: Programming Language :: Python
Classifier: Programming Language :: Python :: 3
Classifier: Programming Language :: Python :: 3.6
Classifier: Programming Language :: Python :: 3.7
Classifier: Programming Language :: Python :: 3.8
Classifier: Framework :: Jupyter
Requires-Python: >=3.6
Requires-Dist: numpy (>=1.9)
Requires-Dist: matplotlib (>1.5)
Requires-Dist: astropy (!=4.0.1,>=1.0)
Requires-Dist: requests
Requires-Dist: beautifulsoup4
Requires-Dist: python-dateutil
Requires-Dist: lxml
Requires-Dist: ipywidgets (>=7.0.0)
Requires-Dist: ipyevents
Requires-Dist: traitlets
Requires-Dist: reproject (>=0.4)
Requires-Dist: qtpy
Requires-Dist: tornado
Requires-Dist: pytz
Provides-Extra: docs
Requires-Dist: sphinx (>=1.6) ; extra == 'docs'
Requires-Dist: sphinx-automodapi ; extra == 'docs'
Requires-Dist: numpydoc ; extra == 'docs'
Requires-Dist: sphinx-rtd-theme ; extra == 'docs'
Requires-Dist: jupyter-sphinx ; extra == 'docs'
Provides-Extra: lab
Requires-Dist: jupyterlab ; extra == 'lab'
Provides-Extra: qt
Requires-Dist: PyQt5 ; (python_version >= "3") and extra == 'qt'
Requires-Dist: PyQtWebEngine ; (python_version >= "3") and extra == 'qt'
Provides-Extra: test
Requires-Dist: pytest ; extra == 'test'
Requires-Dist: pytest-cov (>=2.6.1) ; extra == 'test'
Requires-Dist: pytest-remotedata (>=0.3.1) ; extra == 'test'
